lock.v
module lock(
    input clk,
    input rst,
    input [2:0] btn,
    output led_open,
    output led_error
);
localparam STATE_IDLE = 3'b000;
localparam STATE_NUM1 = 3'b001;
localparam STATE_NUM3 = 3'b010;
localparam STATE_OPEN = 3'b011;
localparam STATE_ERROR = 3'b100;
reg[2:0] current_state;
reg[2:0] next_state;

always @(posedge clk or posedge rst) begin
    if (rst)
    current_state <= STATE_IDLE;
    else
    current_state <= next_state;
end 

always @(*) begin
    next_state = current_state;
    case(current_state)
    STATE_IDLE : begin
        if (btn[0])
        next_state = STATE_NUM1;
        else if (btn[1] || btn[2])
        next_state = STATE_ERROR;
    end
    STATE_NUM1 : begin
        if (btn[1])
        next_state = STATE_NUM3;
        else if (btn[0] || btn[2])
        next_state = STATE_ERROR;
    end
    STATE_NUM3 : begin
        if (btn[2])
        next_state = STATE_OPEN;
        else if (btn[0] || btn[1])
        next_state = STATE_ERROR;
    end
    STATE_OPEN: begin
        next_state = STATE_OPEN;
    end
    STATE_ERROR: begin
        next_state = STATE_ERROR;
    end
    default: begin
        next_state = STATE_IDLE;
    end
    endcase
end

assign led_open = (current_state == STATE_OPEN);
assign led_error = (current_state == STATE_ERROR);

endmodule

lock_tb.v
`timescale 1ns / 1ps

module lock_tb;
reg clk = 0;
reg rst;
reg [2:0] btn;
wire led_open;
wire led_error;

lock uut(
    .clk(clk),
    .rst(rst),
    .btn(btn),
    .led_open(led_open),
    .led_error(led_error)
);

always begin
    #5 clk = ~clk;
end

initial begin
    $dumpfile("lock_tb.vcd");
    $dumpvars(0, lock_tb);
    
    rst=1;
    #15;
    rst=0;
    btn=3'b000;
    #10;

    btn=3'b001;
    #10;
    btn=3'b000;
    #10;

    btn=3'b010;
    #10;
    btn=3'b000;
    #10;

    btn=3'b100;
    #10;
    btn=3'b000;
    #20;



    rst=1;
    #15;
    rst=0;
    btn=3'b000;
    #10;

    btn=3'b001;
    #10;
    btn=3'b000;
    #10;

    btn=3'b001;
    #10;
    btn=3'b000;
    #20;

    #50;
    $finish;
end

endmodule

lock_tb.vcd
$date
	Thu Jun 18 17:51:13 2026
$end
$version
	Icarus Verilog
$end
$timescale
	1ps
$end
$scope module lock_tb $end
$var wire 1 ! led_open $end
$var wire 1 " led_error $end
$var reg 3 # btn [2:0] $end
$var reg 1 $ clk $end
$var reg 1 % rst $end
$scope module uut $end
$var wire 3 & btn [2:0] $end
$var wire 1 $ clk $end
$var wire 1 % rst $end
$var wire 1 ! led_open $end
$var wire 1 " led_error $end
$var parameter 3 ' STATE_ERROR $end
$var parameter 3 ( STATE_IDLE $end
$var parameter 3 ) STATE_NUM1 $end
$var parameter 3 * STATE_NUM3 $end
$var parameter 3 + STATE_OPEN $end
$var reg 3 , current_state [2:0] $end
$var reg 3 - next_state [2:0] $end
$upscope $end
$upscope $end
$enddefinitions $end
$comment Show the parameter values. $end
$dumpall
b11 +
b10 *
b1 )
b0 (
b100 '
$end
#0
$dumpvars
b0 -
b0 ,
bx &
1%
0$
bx #
0"
0!
$end
#5000
1$
#10000
0$
#15000
1$
b0 #
b0 &
0%
#20000
0$
#25000
b1 ,
b100 -
1$
b1 #
b1 &
#30000
0$
#35000
b1 -
1$
b0 #
b0 &
#40000
0$
#45000
b10 ,
b100 -
1$
b10 #
b10 &
#50000
0$
#55000
b10 -
1$
b0 #
b0 &
#60000
0$
#65000
1!
b11 ,
b11 -
1$
b100 #
b100 &
#70000
0$
#75000
1$
b0 #
b0 &
#80000
0$
#85000
1$
#90000
0$
#95000
b0 -
0!
b0 ,
1$
1%
#100000
0$
#105000
1$
#110000
0$
0%
#115000
1$
#120000
b1 -
0$
b1 #
b1 &
#125000
b100 -
b1 ,
1$
#130000
b1 -
0$
b0 #
b0 &
#135000
1$
#140000
b100 -
0$
b1 #
b1 &
#145000
1"
b100 ,
1$
#150000
0$
b0 #
b0 &
